cases/case_1.py
cases/case_2.py
cases/case_3.py
cases/case_4.py
cases/icons.py
cases/manuscript_figure.py
molpub/__init__.py
molpub/handles.py
molpub/layouts.py
molpub/windows.py
tests/test_handles.py
PyMOL_PUB-1.2.dist-info/LICENSE
PyMOL_PUB-1.2.dist-info/METADATA
PyMOL_PUB-1.2.dist-info/WHEEL
PyMOL_PUB-1.2.dist-info/top_level.txt
PyMOL_PUB-1.2.dist-info/RECORD
