Metadata-Version: 2.1
Name: PyMOL-PUB
Version: 1.2
Summary: Rapid generation of high-quality structure figures for publication with PyMOL-PUB
Home-page: https://github.com/BGI-SynBio/PyMOL-PUB
Author: Haoling Zhang
Author-email: zhanghaoling@genomics.cn
License: GPL
Keywords: pymol,pymol-pub,matplotlib,structure-cluster,structure-alignment,manuscript-figure
Classifier: License :: OSI Approved :: GNU General Public License (GPL)
Classifier: Programming Language :: Python :: 3
Classifier: Operating System :: OS Independent
License-File: LICENSE
Requires-Dist: numpy
Requires-Dist: pymol
Requires-Dist: pillow
Requires-Dist: biopython
Requires-Dist: matplotlib
